transsmart_connector/__init__.py
transsmart_connector/test.py
transsmart_connector/transsmart_connector.py
transsmart_connector-0.1.4.dist-info/METADATA
transsmart_connector-0.1.4.dist-info/WHEEL
transsmart_connector-0.1.4.dist-info/top_level.txt
transsmart_connector-0.1.4.dist-info/RECORD
